<?xml version="1.0" encoding="UTF-8"?>
<Entities
 build="b535"
 majorVersion="8"
 minorVersion="3"
 modelPersistenceProviderPackage="H2PersistenceProviderPackage"
 revision="2"
 schemaVersion="1030"
 universal="">
    <Mashups>
        <Mashup
         aspect.mashupType="page"
         columns="0.0"
         description=""
         documentationContent=""
         homeMashup=""
         lastModifiedDate="2019-10-01T12:11:13.084Z"
         name="VendingComplaintConfirm"
         projectName=""
         rows="0.0"
         tags="Applications:AcmeVending">
            <avatar></avatar>
            <DesignTimePermissions>
                <Create></Create>
                <Read></Read>
                <Update></Update>
                <Delete></Delete>
                <Metadata></Metadata>
            </DesignTimePermissions>
            <RunTimePermissions></RunTimePermissions>
            <VisibilityPermissions>
                <Visibility></Visibility>
            </VisibilityPermissions>
            <ConfigurationTableDefinitions></ConfigurationTableDefinitions>
            <ConfigurationTables></ConfigurationTables>
            <ParameterDefinitions></ParameterDefinitions>
            <Things></Things>
            <ThingShapes></ThingShapes>
            <ThingTemplates></ThingTemplates>
            <mashupContent>
            <![CDATA[
            {
              "Data" : { },
              "DataBindings" : [ ],
              "Events" : [ ],
              "UI" : {
                "Properties" : {
                  "Area" : "Mashup",
                  "Height" : 310,
                  "Id" : "mashup-root",
                  "Left" : 0,
                  "Tags" : [ {
                    "vocabulary" : "Applications",
                    "vocabularyTerm" : "AcmeVending"
                  } ],
                  "Target" : "VendingComplaintFrame",
                  "Top" : 0,
                  "Type" : "mashup",
                  "Width" : 250,
                  "Z-index" : 10,
                  "__TypeDisplayName" : "Mashup",
                  "id_index" : 1
                },
                "Widgets" : [ {
                  "Properties" : {
                    "Alignment" : "center",
                    "Area" : "UI",
                    "Height" : 57,
                    "Id" : "Label-1",
                    "Left" : 45,
                    "Style" : "AcmeVendingExtraLarge",
                    "Text" : "Thank You For Your Feedback",
                    "Top" : 115,
                    "Type" : "label",
                    "Width" : 150,
                    "Z-index" : 10,
                    "__TypeDisplayName" : "Label"
                  },
                  "Widgets" : [ ]
                } ]
              },
              "mashupType" : "page"
            }
            ]]>
            </mashupContent>
        </Mashup>
    </Mashups>
</Entities>
